{
	"cmake" : 
	{
		"generator" : 
		{
			"multiConfig" : true,
			"name" : "Visual Studio 18 2026",
			"platform" : "x64"
		},
		"paths" : 
		{
			"cmake" : "X:/vs2026/src/Common7/IDE/CommonExtensions/Microsoft/CMake/CMake/bin/cmake.exe",
			"cpack" : "X:/vs2026/src/Common7/IDE/CommonExtensions/Microsoft/CMake/CMake/bin/cpack.exe",
			"ctest" : "X:/vs2026/src/Common7/IDE/CommonExtensions/Microsoft/CMake/CMake/bin/ctest.exe",
			"root" : "X:/vs2026/src/Common7/IDE/CommonExtensions/Microsoft/CMake/CMake/share/cmake-4.1"
		},
		"version" : 
		{
			"isDirty" : false,
			"major" : 4,
			"minor" : 1,
			"patch" : 1,
			"string" : "4.1.1-msvc1",
			"suffix" : "msvc1"
		}
	},
	"objects" : 
	[
		{
			"jsonFile" : "codemodel-v2-3e97d8e0cd9b4ee2022d.json",
			"kind" : "codemodel",
			"version" : 
			{
				"major" : 2,
				"minor" : 8
			}
		},
		{
			"jsonFile" : "cache-v2-ea39b763b2cae7ae2cb4.json",
			"kind" : "cache",
			"version" : 
			{
				"major" : 2,
				"minor" : 0
			}
		},
		{
			"jsonFile" : "cmakeFiles-v1-1f2e4af43b46f3d7f9eb.json",
			"kind" : "cmakeFiles",
			"version" : 
			{
				"major" : 1,
				"minor" : 1
			}
		},
		{
			"jsonFile" : "toolchains-v1-afe18f5e9b13a7246853.json",
			"kind" : "toolchains",
			"version" : 
			{
				"major" : 1,
				"minor" : 0
			}
		}
	],
	"reply" : 
	{
		"client-vscode" : 
		{
			"query.json" : 
			{
				"requests" : 
				[
					{
						"kind" : "cache",
						"version" : 2
					},
					{
						"kind" : "codemodel",
						"version" : 2
					},
					{
						"kind" : "toolchains",
						"version" : 1
					},
					{
						"kind" : "cmakeFiles",
						"version" : 1
					}
				],
				"responses" : 
				[
					{
						"jsonFile" : "cache-v2-ea39b763b2cae7ae2cb4.json",
						"kind" : "cache",
						"version" : 
						{
							"major" : 2,
							"minor" : 0
						}
					},
					{
						"jsonFile" : "codemodel-v2-3e97d8e0cd9b4ee2022d.json",
						"kind" : "codemodel",
						"version" : 
						{
							"major" : 2,
							"minor" : 8
						}
					},
					{
						"jsonFile" : "toolchains-v1-afe18f5e9b13a7246853.json",
						"kind" : "toolchains",
						"version" : 
						{
							"major" : 1,
							"minor" : 0
						}
					},
					{
						"jsonFile" : "cmakeFiles-v1-1f2e4af43b46f3d7f9eb.json",
						"kind" : "cmakeFiles",
						"version" : 
						{
							"major" : 1,
							"minor" : 1
						}
					}
				]
			}
		}
	}
}
